pnap_rancher_solution_api/__init__.py
pnap_rancher_solution_api/api_client.py
pnap_rancher_solution_api/api_response.py
pnap_rancher_solution_api/configuration.py
pnap_rancher_solution_api/exceptions.py
pnap_rancher_solution_api/py.typed
pnap_rancher_solution_api/rest.py
pnap_rancher_solution_api/version.py
pnap_rancher_solution_api/api/__init__.py
pnap_rancher_solution_api/api/clusters_api.py
pnap_rancher_solution_api/models/__init__.py
pnap_rancher_solution_api/models/cluster.py
pnap_rancher_solution_api/models/delete_result.py
pnap_rancher_solution_api/models/error.py
pnap_rancher_solution_api/models/node.py
pnap_rancher_solution_api/models/node_pool.py
pnap_rancher_solution_api/models/rancher_cluster_certificates.py
pnap_rancher_solution_api/models/rancher_cluster_config.py
pnap_rancher_solution_api/models/rancher_server_metadata.py
pnap_rancher_solution_api/models/ssh_config.py
pnap_rancher_solution_api/models/workload_cluster_config.py
pnap_rancher_solution_api-2.0.4.dist-info/METADATA
pnap_rancher_solution_api-2.0.4.dist-info/WHEEL
pnap_rancher_solution_api-2.0.4.dist-info/top_level.txt
pnap_rancher_solution_api-2.0.4.dist-info/RECORD
